usda/__init__.py
usda/base.py
usda/client.py
usda/domain.py
usda/enums.py
usda/pagination.py
python_usda-0.4.6.dist-info/LICENSE
python_usda-0.4.6.dist-info/METADATA
python_usda-0.4.6.dist-info/WHEEL
python_usda-0.4.6.dist-info/top_level.txt
python_usda-0.4.6.dist-info/RECORD
