Metadata-Version: 2.1
Name: python-usda
Version: 0.4.6
Summary: A fork of pygov focused on USDA nutritional database API
Home-page: https://gitlab.com/Lucidiot/python-usda
Author: Lucidiot
License: GNU General Public License 3
Project-URL: Source Code, https://gitlab.com/Lucidiot/python-usda
Project-URL: GitHub Mirror, https://github.com/Lucidiot/python-usda
Project-URL: Gitter Chat, https://gitter.im/BrainshitPseudoScience/Lobby
Keywords: api usda nutrition food
Platform: UNKNOWN
Classifier: Development Status :: 5 - Production/Stable
Classifier: License :: OSI Approved :: GNU General Public License v3 (GPLv3)
Classifier: Natural Language :: English
Classifier: Intended Audience :: Developers
Classifier: Programming Language :: Python :: 3
Classifier: Programming Language :: Python :: 3 :: Only
Classifier: Programming Language :: Python :: 3.4
Classifier: Programming Language :: Python :: 3.5
Classifier: Programming Language :: Python :: 3.6
Classifier: Programming Language :: Python :: 3.7
Requires-Python: >=3.4
Requires-Dist: requests (>=2.16.0)
Provides-Extra: dev
Requires-Dist: pytest ; extra == 'dev'
Requires-Dist: pytest-cov ; extra == 'dev'
Requires-Dist: pytest-runner ; extra == 'dev'
Requires-Dist: httmock ; extra == 'dev'
Requires-Dist: flake8 (>=3.5) ; extra == 'dev'
Requires-Dist: doc8 (>=0.8) ; extra == 'dev'
Requires-Dist: codecov ; extra == 'dev'
Requires-Dist: Sphinx (>=1.8.1) ; extra == 'dev'
